voxu/__init__.py
voxu/database.py
voxu/middleware.py
voxu/models.py
voxu/voxu_ui.py
voxu-0.1.8.dist-info/LICENSE
voxu-0.1.8.dist-info/METADATA
voxu-0.1.8.dist-info/WHEEL
voxu-0.1.8.dist-info/top_level.txt
voxu-0.1.8.dist-info/RECORD
