Metadata-Version: 2.1
Name: voxu
Version: 0.1.8
Home-page: https://github.com/yorubadeveloper/voxu
Author: Yoruba Developer
Keywords: Python,Flask,Logging,SQLAlchemy,PostgreSQL
License-File: LICENSE
Requires-Dist: sqlalchemy
Requires-Dist: flask
Requires-Dist: psycopg2-binary
